AUTHORS
CHANGELOG.txt
DESCRIPTION
LICENSE
MANIFEST.in
setup.py
django_time_out.egg-info/PKG-INFO
django_time_out.egg-info/SOURCES.txt
django_time_out.egg-info/dependency_links.txt
django_time_out.egg-info/requires.txt
django_time_out.egg-info/top_level.txt
time_out/__init__.py
time_out/admin.py
time_out/middleware.py
time_out/models.py
time_out/urls.py
time_out/views.py
time_out/templates/down_time/down_time.html
time_out/tests/__init__.py
time_out/tests/factories.py
time_out/tests/models_tests.py
time_out/tests/runtests.py
time_out/tests/south_settings.py
time_out/tests/test_settings.py
time_out/tests/urls.py
time_out/tests/test_app/__init__.py
time_out/tests/test_app/models.py
time_out/tests/test_app/templates/400.html
time_out/tests/test_app/templates/500.html