Metadata-Version: 1.0
Name: django-time-out
Version: 0.1.5
Summary: A reusable Django that allows you to put your Django site into maintenance mode.
